liger_kernel/__init__.py
liger_kernel/env_report.py
liger_kernel/utils.py
liger_kernel/chunked_loss/README.md
liger_kernel/chunked_loss/__init__.py
liger_kernel/chunked_loss/cosine_similarity_loss.py
liger_kernel/chunked_loss/cpo_loss.py
liger_kernel/chunked_loss/dpo_loss.py
liger_kernel/chunked_loss/functional.py
liger_kernel/chunked_loss/fused_linear_distillation.py
liger_kernel/chunked_loss/fused_linear_ppo.py
liger_kernel/chunked_loss/fused_linear_preference.py
liger_kernel/chunked_loss/fused_linear_unpaired_preference.py
liger_kernel/chunked_loss/grpo_loss.py
liger_kernel/chunked_loss/jsd_loss.py
liger_kernel/chunked_loss/kto_loss.py
liger_kernel/chunked_loss/orpo_loss.py
liger_kernel/chunked_loss/simpo_loss.py
liger_kernel/ops/__init__.py
liger_kernel/ops/cross_entropy.py
liger_kernel/ops/dyt.py
liger_kernel/ops/fused_add_rms_norm.py
liger_kernel/ops/fused_linear_cross_entropy.py
liger_kernel/ops/fused_linear_jsd.py
liger_kernel/ops/fused_neighborhood_attention.py
liger_kernel/ops/geglu.py
liger_kernel/ops/group_norm.py
liger_kernel/ops/grpo_loss.py
liger_kernel/ops/jsd.py
liger_kernel/ops/kl_div.py
liger_kernel/ops/layer_norm.py
liger_kernel/ops/llama4_rope.py
liger_kernel/ops/multi_token_attention.py
liger_kernel/ops/poly_norm.py
liger_kernel/ops/qwen2vl_mrope.py
liger_kernel/ops/rms_norm.py
liger_kernel/ops/rope.py
liger_kernel/ops/softmax.py
liger_kernel/ops/sparsemax.py
liger_kernel/ops/swiglu.py
liger_kernel/ops/tiled_mlp.py
liger_kernel/ops/tvd.py
liger_kernel/ops/utils.py
liger_kernel/ops/backends/README.md
liger_kernel/ops/backends/__init__.py
liger_kernel/ops/backends/registry.py
liger_kernel/ops/backends/_ascend/__init__.py
liger_kernel/ops/backends/_ascend/ascend-ub-manager-design.md
liger_kernel/ops/backends/_ascend/ub_manager.py
liger_kernel/ops/backends/_ascend/ops/__init__.py
liger_kernel/ops/backends/_ascend/ops/embedding.py
liger_kernel/ops/backends/_ascend/ops/geglu.py
liger_kernel/ops/backends/_ascend/ops/llama4_rope.py
liger_kernel_nightly-0.6.4.dev20260130213504.dist-info/LICENSE
liger_kernel_nightly-0.6.4.dev20260130213504.dist-info/METADATA
liger_kernel_nightly-0.6.4.dev20260130213504.dist-info/NOTICE
liger_kernel_nightly-0.6.4.dev20260130213504.dist-info/WHEEL
liger_kernel_nightly-0.6.4.dev20260130213504.dist-info/top_level.txt
liger_kernel_nightly-0.6.4.dev20260130213504.dist-info/RECORD
