Metadata-Version: 2.1
Name: liger_kernel_nightly
Version: 0.6.4.dev20260130213504
Summary: Efficient Triton kernels for LLM Training
License: BSD 2-CLAUSE LICENSE
Project-URL: Homepage, https://github.com/linkedin/Liger-Kernel
License-File: LICENSE
License-File: NOTICE
Requires-Dist: torch>=2.1.2
Requires-Dist: triton>=2.3.1
Provides-Extra: dev
Requires-Dist: transformers<5.0.0,>=4.49.0; extra == "dev"
Requires-Dist: matplotlib>=3.7.2; extra == "dev"
Requires-Dist: ruff>=0.12.0; extra == "dev"
Requires-Dist: pytest>=7.1.2; extra == "dev"
Requires-Dist: pytest-xdist; extra == "dev"
Requires-Dist: pytest-cov; extra == "dev"
Requires-Dist: pytest-asyncio; extra == "dev"
Requires-Dist: pytest-rerunfailures; extra == "dev"
Requires-Dist: datasets>=2.19.2; extra == "dev"
Requires-Dist: seaborn; extra == "dev"
Requires-Dist: mkdocs-material; extra == "dev"
Requires-Dist: torchvision>=0.20; extra == "dev"
Requires-Dist: prek>=0.2.28; extra == "dev"
